odoo/addons/pos_product_quick_info/README.rst
odoo/addons/pos_product_quick_info/__init__.py
odoo/addons/pos_product_quick_info/__manifest__.py
odoo/addons/pos_product_quick_info/i18n/es.po
odoo/addons/pos_product_quick_info/i18n/it.po
odoo/addons/pos_product_quick_info/i18n/pos_product_quick_info.pot
odoo/addons/pos_product_quick_info/models/__init__.py
odoo/addons/pos_product_quick_info/models/pos_config.py
odoo/addons/pos_product_quick_info/models/res_config_settings.py
odoo/addons/pos_product_quick_info/readme/CONFIGURE.rst
odoo/addons/pos_product_quick_info/readme/CONTRIBUTORS.rst
odoo/addons/pos_product_quick_info/readme/DESCRIPTION.rst
odoo/addons/pos_product_quick_info/static/description/banner.png
odoo/addons/pos_product_quick_info/static/description/icon.png
odoo/addons/pos_product_quick_info/static/description/index.html
odoo/addons/pos_product_quick_info/static/img/config.png
odoo/addons/pos_product_quick_info/static/img/info.png
odoo/addons/pos_product_quick_info/static/src/css/pos.css
odoo/addons/pos_product_quick_info/static/src/js/Screens/ProductScreen/ProductItem.js
odoo/addons/pos_product_quick_info/static/src/xml/Screens/ProductScreen/ProductItem.xml
odoo/addons/pos_product_quick_info/views/res_config_settings_view.xml
odoo_addon_pos_product_quick_info-16.0.1.0.2.dist-info/METADATA
odoo_addon_pos_product_quick_info-16.0.1.0.2.dist-info/WHEEL
odoo_addon_pos_product_quick_info-16.0.1.0.2.dist-info/top_level.txt
odoo_addon_pos_product_quick_info-16.0.1.0.2.dist-info/RECORD
